{"sa6iGPLXxOUkgcJJGgoC2A==":"oddjobsasset-1.png","Nir6K1ZoNZ14ZGBrhdNzCw==":"job-ad.png","PNyKc2XEBO63+f+kLvGMYQ==":"job-ad2.png","WFF3QMCvs0FTAHZJm7bSKw==":"logo2asset-3.png","5PYhI17fR0bty68L4XMnMw==":"logoflatasset-6.png","Fb9MjXsrmH4lvWtyrMBLpQ==":"logoflat2asset-7.png","e/unwqhXIr+7soTmWbs4LQ==":"logoflat3asset-8.png","rV3SZpILLGhX9u9mb34rNA==":"logoflat5asset-10.png","uCvH95eSaH/ILHEZNd3ohw==":"logoflat6asset-12.png","/tMKGSRMhTw6YMFa2CX7+w==":"logoflat7asset-13.png","Gzt4B+fKlAORWkqzSzWk4w==":"mobileasset-1.png"}